likelihood_combiner/__init__.py
likelihood_combiner/cluster.py
likelihood_combiner/combiner.py
likelihood_combiner/io.py
likelihood_combiner/jfactor.py
likelihood_combiner/local.py
likelihood_combiner/plotter.py
likelihood_combiner/reader.py
likelihood_combiner/sensitivity.py
likelihood_combiner/utils.py
likelihood_combiner/version.py
likelihood_combiner/resources/Bonnivard/BootesI_Dalphaint_cls.output
likelihood_combiner/resources/Bonnivard/BootesI_Jalphaint_cls.output
likelihood_combiner/resources/Bonnivard/CanesVenaticiII_Dalphaint_cls.output
likelihood_combiner/resources/Bonnivard/CanesVenaticiII_Jalphaint_cls.output
likelihood_combiner/resources/Bonnivard/CanesVenaticiI_Dalphaint_cls.output
likelihood_combiner/resources/Bonnivard/CanesVenaticiI_Jalphaint_cls.output
likelihood_combiner/resources/Bonnivard/Carina_Dalphaint_cls.output
likelihood_combiner/resources/Bonnivard/Carina_Jalphaint_cls.output
likelihood_combiner/resources/Bonnivard/ComaBerenices_Dalphaint_cls.output
likelihood_combiner/resources/Bonnivard/ComaBerenices_Jalphaint_cls.output
likelihood_combiner/resources/Bonnivard/Draco_Dalphaint_cls.output
likelihood_combiner/resources/Bonnivard/Draco_Jalphaint_cls.output
likelihood_combiner/resources/Bonnivard/Fornax_Dalphaint_cls.output
likelihood_combiner/resources/Bonnivard/Fornax_Jalphaint_cls.output
likelihood_combiner/resources/Bonnivard/Hercules_Dalphaint_cls.output
likelihood_combiner/resources/Bonnivard/Hercules_Jalphaint_cls.output
likelihood_combiner/resources/Bonnivard/LeoII_Dalphaint_cls.output
likelihood_combiner/resources/Bonnivard/LeoII_Jalphaint_cls.output
likelihood_combiner/resources/Bonnivard/LeoIV_Dalphaint_cls.output
likelihood_combiner/resources/Bonnivard/LeoIV_Jalphaint_cls.output
likelihood_combiner/resources/Bonnivard/LeoI_Dalphaint_cls.output
likelihood_combiner/resources/Bonnivard/LeoI_Jalphaint_cls.output
likelihood_combiner/resources/Bonnivard/LeoT_Dalphaint_cls.output
lklcom-0.5.2.dist-info/LICENSE
lklcom-0.5.2.dist-info/METADATA
lklcom-0.5.2.dist-info/WHEEL
lklcom-0.5.2.dist-info/top_level.txt
lklcom-0.5.2.dist-info/RECORD
