Metadata-Version: 2.1
Name: lklcom
Version: 0.5.2
Summary: LikelihoodCombiner combines DM-related likelihoods from different experiments.
Home-page: https://github.com/TjarkMiener/likelihood_combiner
Author: Tjark Miener
Author-email: tmiener@ucm.es
License: GPL-3.0
Platform: UNKNOWN
Requires-Dist: matplotlib
Requires-Dist: numpy (>=1.15.0)
Requires-Dist: scipy
Requires-Dist: jupyter
Requires-Dist: pandas
Requires-Dist: pyyaml
Requires-Dist: tables
